config_lib/__init__.py
config_lib/base.py
config_lib/py.typed
config_lib/sources/__init__.py
config_lib/sources/cli.py
config_lib/sources/env.py
config_lib/sources/yaml.py
config_lib/utils/__init__.py
config_lib/utils/merge.py
config_lib/utils/nest.py
config_lib/utils/types.py
config_lib_msgspec-0.0.8.dist-info/licenses/LICENSE
config_lib_msgspec-0.0.8.dist-info/METADATA
config_lib_msgspec-0.0.8.dist-info/WHEEL
config_lib_msgspec-0.0.8.dist-info/entry_points.txt
config_lib_msgspec-0.0.8.dist-info/top_level.txt
config_lib_msgspec-0.0.8.dist-info/RECORD
