Metadata-Version: 2.4
Name: config-lib-msgspec
Version: 0.0.8
Summary: A lightweight configuration management library for Python applications with multiple sources, type validation, and automatic merging
Author-email: Artem Shestopalov <tema.rastaclaus@gmail.com>
Project-URL: Homepage, https://github.com/rastaclaus/config-lib-msgspec.git
Project-URL: Repository, https://github.com/rastaclaus/config-lib-msgspec.git
Project-URL: Issues, https://github.com/rastaclaus/config-lib-msgspec/issues
Keywords: configuration,config,settings,yaml,environment,cli
Classifier: Development Status :: 3 - Alpha
Classifier: Intended Audience :: Developers
Classifier: Operating System :: OS Independent
Classifier: Programming Language :: Python :: 3.9
Classifier: Programming Language :: Python :: 3.10
Classifier: Programming Language :: Python :: 3.11
Classifier: Topic :: Software Development :: Libraries :: Python Modules
Classifier: Typing :: Typed
Requires-Python: >=3.9
License-File: LICENSE
Requires-Dist: msgspec>=0.19.0
Requires-Dist: pyyaml>=6.0.2
Requires-Dist: typing-extensions>=4.13.0; python_full_version < "3.11"
Provides-Extra: dev
Requires-Dist: pytest>=8.3.5; extra == "dev"
Requires-Dist: coverage>=7.8.0; extra == "dev"
Requires-Dist: ruff>=0.3.0; extra == "dev"
Requires-Dist: mypy>=1.9.0; extra == "dev"
Dynamic: license-file
